PyTerm1.py
pyterm1-1.1.0.dist-info/WHEEL
pyterm1-1.1.0.dist-info/METADATA
pyterm1-1.1.0.dist-info/RECORD
